{"DocumentId":"PurchaseOrder.pdf","ResultsVersion":0,"ResultsDocument":{"Bounds":{"StartPage":0,"PageCount":1,"TextStartIndex":0,"TextLength":2429},"Language":null,"DocumentGroup":"Test","DocumentCategory":"Financial","DocumentTypeId":"Test.Financial.Invoice","DocumentTypeName":"Invoice","DocumentTypeDataVersion":0,"DataVersion":0,"DocumentTypeSource":"Automatic","DocumentTypeField":{"Components":[],"Value":"Invoice","Reference":{"TextStartIndex":0,"TextLength":14,"Tokens":[{"TextStartIndex":0,"TextLength":14,"Page":0,"PageWidth":612.0,"PageHeight":792.0,"Boxes":[[28.276,424.22,67.236,14.28],[28.276,494.792,43.284,14.28]]}]},"DerivedFields":[],"Confidence":0.99666667,"OperatorConfirmed":false,"OcrConfidence":1.0},"Fields":[{"FieldId":"Test.Financial.Invoice.Date","FieldName":"P.O. Date","FieldType":"Date","IsMissing":true,"DataSource":"Automatic","Values":[],"DataVersion":0},{"FieldId":"Test.Financial.Invoice.PONo","FieldName":"P.O. Number","FieldType":"Number","IsMissing":true,"DataSource":"Automatic","Values":[],"DataVersion":0},{"FieldId":"Test.Financial.Invoice.BillingAddress","FieldName":"Billing Address","FieldType":"Address","IsMissing":true,"DataSource":"Automatic","Values":[],"DataVersion":0},{"FieldId":"Test.Financial.Invoice.ShippingAddress","FieldName":"Shipping Address","FieldType":"Address","IsMissing":false,"DataSource":"Automatic","Values":[{"Components":[],"Value":"8755 Dell Road Saline MI 48176 (734)-429-5190","Reference":{"TextStartIndex":0,"TextLength":0,"Tokens":[{"TextStartIndex":0,"TextLength":0,"Page":0,"PageWidth":612.0,"PageHeight":792.0,"Boxes":[[157.0,370.0,18.0,8.0]]},{"TextStartIndex":0,"TextLength":0,"Page":0,"PageWidth":612.0,"PageHeight":792.0,"Boxes":[[156.0,392.0,15.0,9.0]]},{"TextStartIndex":0,"TextLength":0,"Page":0,"PageWidth":612.0,"PageHeight":792.0,"Boxes":[[156.0,409.0,21.0,8.0]]},{"TextStartIndex":0,"TextLength":0,"Page":0,"PageWidth":612.0,"PageHeight":792.0,"Boxes":[[168.0,369.0,24.0,9.0]]},{"TextStartIndex":0,"TextLength":0,"Page":0,"PageWidth":612.0,"PageHeight":792.0,"Boxes":[[167.0,395.0,14.0,10.0]]},{"TextStartIndex":0,"TextLength":0,"Page":0,"PageWidth":612.0,"PageHeight":792.0,"Boxes":[[167.0,410.0,23.0,9.0]]},{"TextStartIndex":0,"TextLength":0,"Page":0,"PageWidth":612.0,"PageHeight":792.0,"Boxes":[[178.0,370.0,60.0,11.0]]}]},"DerivedFields":[{"FieldId":"Address Line 1","Value":"8755 Dell Road 734)-429-5190"},{"FieldId":"City","Value":"Saline"},{"FieldId":"Country","Value":"United States"},{"FieldId":"State / County / Province","Value":"Michigan"},{"FieldId":"Zip Postal Code","Value":"48176"}],"Confidence":0.25,"OperatorConfirmed":false,"OcrConfidence":0.25}],"DataVersion":0},{"FieldId":"Test.Financial.Invoice.VendorAddress","FieldName":"Vendor Address","FieldType":"Address","IsMissing":true,"DataSource":"Automatic","Values":[],"DataVersion":0},{"FieldId":"Test.Financial.Invoice.Items","FieldName":"Items","FieldType":"Table","IsMissing":false,"DataSource":"Automatic","Values":[{"Components":[{"FieldId":"Test.Financial.Invoice.Items.Header","FieldName":"Header","FieldType":"Internal","IsMissing":false,"DataSource":"Automatic","Values":[{"Components":[{"FieldId":"Test.Financial.Invoice.Items.ItemPONo","FieldName":"Item","FieldType":"Number","IsMissing":false,"DataSource":"Automatic","Values":[{"Components":[],"Value":"item-po-no","Reference":{"TextStartIndex":0,"TextLength":0,"Tokens":[]},"DerivedFields":[],"Confidence":-1.0,"OperatorConfirmed":false,"OcrConfidence":-1.0}],"DataVersion":0},{"FieldId":"Test.Financial.Invoice.Items.Qty","FieldName":"Quantity","FieldType":"Number","IsMissing":false,"DataSource":"Automatic","Values":[{"Components":[],"Value":"quantity","Reference":{"TextStartIndex":0,"TextLength":0,"Tokens":[]},"DerivedFields":[],"Confidence":-1.0,"OperatorConfirmed":false,"OcrConfidence":-1.0}],"DataVersion":0},{"FieldId":"Test.Financial.Invoice.Items.Amount","FieldName":"Part Number","FieldType":"Text","IsMissing":false,"DataSource":"Automatic","Values":[{"Components":[],"Value":"Part Number","Reference":{"TextStartIndex":0,"TextLength":0,"Tokens":[]},"DerivedFields":[],"Confidence":1.0,"OperatorConfirmed":false,"OcrConfidence":1.0}],"DataVersion":0},{"FieldId":"Test.Financial.Invoice.Items.Description","FieldName":"Description","FieldType":"Text","IsMissing":false,"DataSource":"Automatic","Values":[{"Components":[],"Value":"description","Reference":{"TextStartIndex":0,"TextLength":0,"Tokens":[]},"DerivedFields":[],"Confidence":-1.0,"OperatorConfirmed":false,"OcrConfidence":-1.0}],"DataVersion":0},{"FieldId":"Test.Financial.Invoice.Items.UnitPrice","FieldName":"Unit Price","FieldType":"Text","IsMissing":false,"DataSource":"Automatic","Values":[{"Components":[],"Value":"unit-price","Reference":{"TextStartIndex":0,"TextLength":0,"Tokens":[]},"DerivedFields":[],"Confidence":-1.0,"OperatorConfirmed":false,"OcrConfidence":-1.0}],"DataVersion":0}],"Value":"","Reference":{"TextStartIndex":0,"TextLength":0,"Tokens":[]},"DerivedFields":[],"Confidence":-1.0,"OperatorConfirmed":false,"OcrConfidence":-1.0}],"DataVersion":0},{"FieldId":"Test.Financial.Invoice.Items.Body","FieldName":"Body","FieldType":"Internal","IsMissing":false,"DataSource":"Automatic","Values":[{"Components":[{"FieldId":"Test.Financial.Invoice.Items.ItemPONo","FieldName":"Item","FieldType":"Number","IsMissing":true,"DataSource":"Automatic","Values":null,"DataVersion":0},{"FieldId":"Test.Financial.Invoice.Items.Qty","FieldName":"Quantity","FieldType":"Number","IsMissing":false,"DataSource":"Automatic","Values":[{"Components":[],"Value":"1.00","Reference":{"TextStartIndex":0,"TextLength":0,"Tokens":[{"TextStartIndex":0,"TextLength":0,"Page":0,"PageWidth":612.0,"PageHeight":792.0,"Boxes":[[307.0,398.0,29.0,10.0]]}]},"DerivedFields":[],"Confidence":0.0,"OperatorConfirmed":false,"OcrConfidence":0.0}],"DataVersion":0},{"FieldId":"Test.Financial.Invoice.Items.Amount","FieldName":"Part Number","FieldType":"Text","IsMissing":true,"DataSource":"Automatic","Values":[],"DataVersion":0},{"FieldId":"Test.Financial.Invoice.Items.Description","FieldName":"Description","FieldType":"Text","IsMissing":false,"DataSource":"Automatic","Values":[{"Components":[],"Value":"INS0000169578 15/16'x600'x.018\"Rehau CP41123 15/16x600x.018\"Rehau CP41123","Reference":{"TextStartIndex":0,"TextLength":0,"Tokens":[{"TextStartIndex":0,"TextLength":0,"Page":0,"PageWidth":612.0,"PageHeight":792.0,"Boxes":[[306.0,124.0,62.0,7.0]]},{"TextStartIndex":0,"TextLength":0,"Page":0,"PageWidth":612.0,"PageHeight":792.0,"Boxes":[[316.0,126.0,98.0,10.0]]},{"TextStartIndex":0,"TextLength":0,"Page":0,"PageWidth":612.0,"PageHeight":792.0,"Boxes":[[316.0,230.0,36.0,10.0]]},{"TextStartIndex":0,"TextLength":0,"Page":0,"PageWidth":612.0,"PageHeight":792.0,"Boxes":[[326.0,128.0,97.0,12.0]]},{"TextStartIndex":0,"TextLength":0,"Page":0,"PageWidth":612.0,"PageHeight":792.0,"Boxes":[[326.0,230.0,35.0,12.0]]}]},"DerivedFields":[],"Confidence":0.4318182,"OperatorConfirmed":false,"OcrConfidence":0.4318182}],"DataVersion":0},{"FieldId":"Test.Financial.Invoice.Items.UnitPrice","FieldName":"Unit Price","FieldType":"Text","IsMissing":false,"DataSource":"Automatic","Values":[{"Components":[],"Value":"29.10","Reference":{"TextStartIndex":0,"TextLength":0,"Tokens":[{"TextStartIndex":0,"TextLength":0,"Page":0,"PageWidth":612.0,"PageHeight":792.0,"Boxes":[[307.0,476.0,19.0,8.0]]}]},"DerivedFields":[],"Confidence":0.111111112,"OperatorConfirmed":false,"OcrConfidence":0.111111112}],"DataVersion":0}],"Value":"","Reference":{"TextStartIndex":0,"TextLength":0,"Tokens":[]},"DerivedFields":[],"Confidence":0.0,"OperatorConfirmed":false,"OcrConfidence":0.0}],"DataVersion":0}],"Value":"","Reference":{"TextStartIndex":0,"TextLength":0,"Tokens":[]},"DerivedFields":[],"Confidence":0.0,"OperatorConfirmed":false,"OcrConfidence":0.0}],"DataVersion":0},{"FieldId":"Test.Financial.Invoice.Currency","FieldName":"Currency","FieldType":"Text","IsMissing":false,"DataSource":"Automatic","Values":[{"Components":[],"Value":"USD","Reference":{"TextStartIndex":0,"TextLength":0,"Tokens":[{"TextStartIndex":0,"TextLength":0,"Page":0,"PageWidth":612.0,"PageHeight":792.0,"Boxes":[[0.0,0.0,0.0,0.0]]}]},"DerivedFields":[],"Confidence":0.86,"OperatorConfirmed":false,"OcrConfidence":0.86}],"DataVersion":0},{"FieldId":"Test.Financial.Invoice.Total","FieldName":"Total","FieldType":"Text","IsMissing":false,"DataSource":"Automatic","Values":[{"Components":[],"Value":"29.10","Reference":{"TextStartIndex":0,"TextLength":0,"Tokens":[{"TextStartIndex":0,"TextLength":0,"Page":0,"PageWidth":612.0,"PageHeight":792.0,"Boxes":[[749.0,553.0,25.0,7.0]]}]},"DerivedFields":[],"Confidence":0.333333343,"OperatorConfirmed":false,"OcrConfidence":0.333333343}],"DataVersion":0}]}}